autojson/__init__.py
autojson/autojson.py
autojson-0.1.2.dist-info/LICENSE
autojson-0.1.2.dist-info/WHEEL
autojson-0.1.2.dist-info/METADATA
autojson-0.1.2.dist-info/RECORD
