Metadata-Version: 2.1
Name: autojson
Version: 0.1.2
Summary: A module in which Python classes define JSON
Home-page: https://github.com/hirahara-taiki/autojson
License: MIT
Author: Hirahara. Taiki
Author-email: hirahara.taiki@gmail.com
Requires-Python: >=3.7,<4.0
Classifier: License :: OSI Approved :: MIT License
Classifier: Programming Language :: Python :: 3
Classifier: Programming Language :: Python :: 3.7
Classifier: Programming Language :: Python :: 3.8
Classifier: Programming Language :: Python :: 3.9
Project-URL: Repository, https://github.com/hirahara-taiki/autojson
